<?xml version="1.0" encoding="ISO-8859-1"?>
<!DOCTYPE sect1 PUBLIC "-//OASIS//DTD DocBook XML V4.5//EN"
  "http://www.oasis-open.org/docbook/xml/4.5/docbookx.dtd" [
  <!ENTITY % general-entities SYSTEM "../../general.ent">
  %general-entities;
]>

<sect1 id="ch-materials-patches-common">
  <?dbhtml filename="patches.html"?>

  <title>Needed Patches</title>

  <para>In addition to the packages, several patches are also required.
  These patches correct any mistakes in the packages that should be
  fixed by the maintainer. The patches also make small modifications to
  make the packages easier to work with. The following patches will be
  needed to build a CLFS system:</para>

  <variablelist role="materials">

    <varlistentry>
      <term>Busybox Config Patch - <token>&busybox-config-patch-size;</token>:</term>
      <listitem>
        <para>Download: <ulink
        url="&patches-root;&busybox-config-patch;"/></para>
        <para>MD5 sum: <literal>&busybox-config-patch-md5;</literal></para>
      </listitem>
    </varlistentry>

<!--
    <varlistentry>
      <term>Busybox Fixes Patch - <token>&busybox-fixes-patch-size;</token>:</term>
      <listitem>
        <para>Download: <ulink
        url="&patches-root;&busybox-fixes-patch;"/></para>
        <para>MD5 sum: <literal>&busybox-fixes-patch-md5;</literal></para>
      </listitem>
    </varlistentry>
-->

    <varlistentry>
      <term>Iana-Etc Update Patch - <token>&iana-etc-update-patch-size;</token>:</term>
      <listitem>
        <para>Download: <ulink
        url="&patches-root;&iana-etc-update-patch;"/></para>
        <para>MD5 sum: <literal>&iana-etc-update-patch-md5;</literal></para>
      </listitem>
    </varlistentry>

    <varlistentry>
      <term>uClibc Configs Patch - <token>&uclibc-configs-patch-size;</token>:</term>
      <listitem>
        <para>Download: <ulink
        url="&patches-root;&uclibc-configs-patch;"/></para>
        <para>MD5 sum: <literal>&uclibc-configs-patch-md5;</literal></para>
      </listitem>
    </varlistentry>

  </variablelist>

  <para os="a">Total size of these patches: about <returnvalue/></para>

</sect1>
